asd/__init__.py
asd/core/__init__.py
asd/core/constants.py
asd/core/dipolar_interactions.py
asd/core/geometry.py
asd/core/gneb.py
asd/core/hamiltonian.py
asd/core/llg_advanced.py
asd/core/llg_simple.py
asd/core/log_general.py
asd/core/monte_carlo.py
asd/core/random_vectors.py
asd/core/shell_exchange.py
asd/core/spin_configurations.py
asd/core/spin_correlations.py
asd/core/topological_charge.py
asd/data_base/exchange_for_Cr2I3X3.py
asd/data_base/exchange_for_CrI3.py
asd/data_base/exchange_for_CrMnI6_U2.py
asd/data_base/exchange_for_CrMnI6_U4.py
asd/data_base/exchange_for_CrMnI6_rect.py
asd/data_base/exchange_for_Gd2C.py
asd/data_base/exchange_for_MnI2.py
asd/data_base/exchange_for_NiI2.py
asd/data_base/exchange_for_RuCl3.py
asd/data_base/exchange_for_VOI2.py
asd/data_base/exchange_for_kagome.py
asd/data_base/exchange_for_skx.py
asd/mpi/mpi_tools.py
asd/utility/Swq.py
asd/utility/__init__.py
asd/utility/analyze_Spirit_results.py
asd/utility/asd_arguments.py
asd/utility/auxiliary_colormaps.py
asd/utility/curve_fit.py
asd/utility/four_state_tools.py
asd/utility/head_figlet.py
asd/utility/mag_thermal.py
asd/utility/ovf_tools.py
asd/utility/plot_tools_3d.py
asd/utility/post_llg.py
asd/utility/post_mc.py
asd/utility/spin_visualize_tools.py
asd/utility/spirit_tool.py
pyasd-0.0.8.dist-info/LICENSE
pyasd-0.0.8.dist-info/METADATA
pyasd-0.0.8.dist-info/WHEEL
pyasd-0.0.8.dist-info/top_level.txt
pyasd-0.0.8.dist-info/RECORD
