Metadata-Version: 2.1
Name: pyasd
Version: 0.0.8
Summary: A python-based spin dynamics simulator
Home-page: https://to_be_posted
Download-URL: https://on_request
Author: Shunhong Zhang
Author-email: zhangshunhong.pku@gmail.com
License: LICENSE
Keywords: spin dynamics simulation
Platform: linux
Classifier: Programming Language :: Python :: 3
License-File: LICENSE
Requires-Dist: numpy
Requires-Dist: scipy
Requires-Dist: matplotlib
Requires-Dist: mpi4py
Requires-Dist: pyfiglet
Requires-Dist: ovf
